semi_ate_installer/__init__.py
semi_ate_installer/cli.py
semi_ate_installer/channel/__init__.py
semi_ate_installer/channel/repository.py
semi_ate_installer/environment/__init__.py
semi_ate_installer/environment/handler.py
semi_ate_installer/state/__init__.py
semi_ate_installer/state/base.py
semi_ate_installer/state/state_machine.py
semi_ate_installer/utils/__init__.py
semi_ate_installer/utils/commands.py
semi_ate_installer/utils/packages.py
semi_ate_installer/utils/profiles.py
semi_ate_installer-0.0.23.dist-info/METADATA
semi_ate_installer-0.0.23.dist-info/WHEEL
semi_ate_installer-0.0.23.dist-info/entry_points.txt
semi_ate_installer-0.0.23.dist-info/licenses/LICENSE
semi_ate_installer-0.0.23.dist-info/RECORD
