Metadata-Version: 2.4
Name: semi-ate-installer
Version: 0.0.23
Summary: Semi ATE Installer package for ATE Projects
Author-email: The Semi-ATE Project Contributors <ate.organization@gmail.com>
License-Expression: GPL-2.0-only
License-File: LICENSE
Keywords: ATE,Automatic,Equipment,Plugin,Semiconductor,Spyder,Test
Classifier: License :: OSI Approved :: GNU General Public License v2 (GPLv2)
Requires-Dist: hatchling
Requires-Dist: mamba
Requires-Dist: packaging
Requires-Dist: pyfiglet>=0.8
Requires-Dist: questionary==1.10.0
